MANIFEST.in
README.rst
setup.py
templateme/__init__.py
templateme/__main__.py
templateme/arguments.py
templateme/configuration.py
templateme/console.py
templateme/manager.py
templateme/manifest.py
templateme.egg-info/PKG-INFO
templateme.egg-info/SOURCES.txt
templateme.egg-info/dependency_links.txt
templateme.egg-info/entry_points.txt
templateme.egg-info/requires.txt
templateme.egg-info/top_level.txt
templateme/containers/__init__.py
templateme/containers/abstract.py
templateme/containers/path.py
templateme/containers/resource.py
templateme/templates/cpp/Makefile
templateme/templates/cpp/main.cpp
templateme/templates/cpp/manifest.json
templateme/templates/cpp-class/manifest.json
templateme/templates/cpp-class/lib/%CLASS%.h
templateme/templates/cpp-class/src/%CLASS%.cpp
templateme/templates/python3/manifest.json
templateme/templates/python3/setup.py
templateme/templates/python3-consoleapp/manifest.json
templateme/templates/python3-consoleapp/%MODULE%/__main__.py
templateme/templates/python3-consoleapp/%MODULE%/console.py
templateme/templates/python3-tests/manifest.json
templateme/templates/python3-tests/tests/__init__.py
templateme/templates/python3-tests/tests/__main__.py
templateme/templates/python3-travis/.travis.yml
templateme/templates/python3-travis/manifest.json
templateme/templates/python3/%MODULE%/__init__.py
templateme/templates/readme/README.md
templateme/templates/readme/manifest.json
templateme/tests/__init__.py
templateme/tests/__main__.py
templateme/tests/arguments.py
templateme/tests/console.py
templateme/tests/templates.py