Metadata-Version: 1.2
Name: templateme
Version: 0.0.7
Summary: Template Me - module with template for your favourite projects.
Home-page: https://github.com/rafyco/templateme
Author: Rafal Kobel
Author-email: rafalkobel@rafyco.pl
License: GNU
Project-URL: Bug Reports, https://github.com/rafyco/templateme/issues
Project-URL: Source, https://github.com/rafyco/templateme
Project-URL: Documentation, https://templateme.readthedocs.io/en/latest/
Keywords: template,programming,fast
Platform: Any
Classifier: Environment :: Console
Classifier: Development Status :: 3 - Alpha
Classifier: Intended Audience :: Developers
Classifier: Intended Audience :: Science/Research
Classifier: Programming Language :: Python :: 3
Classifier: Programming Language :: Python :: 3.5
Classifier: Programming Language :: Python :: 3.6
Classifier: License :: OSI Approved :: MIT License
Classifier: Topic :: Terminals
Requires-Python: >=3.5
